runpandarun/__init__.py
runpandarun/cli.py
runpandarun/datapatch.py
runpandarun/exceptions.py
runpandarun/io.py
runpandarun/playbook.py
runpandarun/types.py
runpandarun/util.py
runpandarun-0.7.0.dist-info/METADATA
runpandarun-0.7.0.dist-info/WHEEL
runpandarun-0.7.0.dist-info/entry_points.txt
runpandarun-0.7.0.dist-info/licenses/LICENSE
runpandarun-0.7.0.dist-info/RECORD
