Metadata-Version: 2.4
Name: runpandarun
Version: 0.7.0
Summary: Tell pandas what to do – easy tabular data I/O playbooks
License-Expression: MIT
License-File: LICENSE
Author: Simon Wörpel
Author-email: simon.woerpel@pm.me
Requires-Python: >=3.11,<3.14
Classifier: Intended Audience :: Developers
Classifier: Operating System :: OS Independent
Classifier: Programming Language :: Python
Classifier: Programming Language :: Python :: 3.10
Classifier: Programming Language :: Python :: 3.11
Classifier: Programming Language :: Python :: 3.12
Classifier: Programming Language :: Python :: 3.13
Requires-Dist: banal (>=1.0.6,<2.0.0)
Requires-Dist: datapatch (>=1.2.4,<2.0.0)
Requires-Dist: fsspec (>=2025.3.2,<2027.0.0)
Requires-Dist: normality (>=3.0.2,<4.0.0)
Requires-Dist: openpyxl (>=3.1.5,<4.0.0)
Requires-Dist: orjson (>=3.11.6,<4.0.0)
Requires-Dist: pandas (>=3.0.0,<4.0.0)
Requires-Dist: pydantic (>=2.12.5,<3.0.0)
Requires-Dist: pyicu (>=2.16,<3.0)
Requires-Dist: requests (>=2.32.5,<3.0.0)
Requires-Dist: rigour (>=1.6.2,<2.0.0)
Requires-Dist: s3fs (>=2026.1.0,<2027.0.0)
Requires-Dist: sqlalchemy (>=2.0.46,<3.0.0)
Requires-Dist: typer (>=0.21.1,<0.22.0)
Requires-Dist: xlrd (>=2.0.2,<3.0.0)
Project-URL: Documentation, https://docs.investigraph.dev/runpandarun
Project-URL: Homepage, https://investigraph.dev
Project-URL: Issues, https://github.com/simonwoerpel/runpandarun/issues
Project-URL: Repository, https://github.com/simonwoerpel/runpandarun
